omniblack/notify.py
omniblack.notify-0.0.2.dist-info/LICENSE.txt
omniblack.notify-0.0.2.dist-info/METADATA
omniblack.notify-0.0.2.dist-info/WHEEL
omniblack.notify-0.0.2.dist-info/omniblack_package.json
omniblack.notify-0.0.2.dist-info/omniblack_package.yaml
omniblack.notify-0.0.2.dist-info/top_level.txt
omniblack.notify-0.0.2.dist-info/RECORD
