Metadata-Version: 2.1
Name: omniblack.notify
Version: 0.0.2
Author-email: Terry Patterson <Terryp@wegrok.net>
License: 
Project-URL: Homepage, https://gitlab.com/terryp/terry/-/tree/next/lib/notify
Project-URL: Repository, https://gitlab.com/terryp/terry.git
Requires-Python: ~=3.10
License-File: LICENSE.txt
Requires-Dist: jeepney
